odoo10_addon_account_invoice_overdue_warn-10.0.1.0.0.99.dev2-py3.8-nspkg.pth
odoo/addons/account_invoice_overdue_warn/README.rst
odoo/addons/account_invoice_overdue_warn/__init__.py
odoo/addons/account_invoice_overdue_warn/__manifest__.py
odoo/addons/account_invoice_overdue_warn/i18n/account_invoice_overdue_warn.pot
odoo/addons/account_invoice_overdue_warn/i18n/fr.po
odoo/addons/account_invoice_overdue_warn/models/__init__.py
odoo/addons/account_invoice_overdue_warn/models/res_partner.py
odoo/addons/account_invoice_overdue_warn/readme/CONTRIBUTORS.rst
odoo/addons/account_invoice_overdue_warn/readme/DESCRIPTION.rst
odoo/addons/account_invoice_overdue_warn/static/description/icon.png
odoo/addons/account_invoice_overdue_warn/static/description/index.html
odoo/addons/account_invoice_overdue_warn/static/description/partner_overdue_invoice_warn.png
odoo/addons/account_invoice_overdue_warn/tests/__init__.py
odoo/addons/account_invoice_overdue_warn/tests/test_overdue_warn.py
odoo/addons/account_invoice_overdue_warn/views/res_partner.xml
odoo10_addon_account_invoice_overdue_warn-10.0.1.0.0.99.dev2.dist-info/METADATA
odoo10_addon_account_invoice_overdue_warn-10.0.1.0.0.99.dev2.dist-info/WHEEL
odoo10_addon_account_invoice_overdue_warn-10.0.1.0.0.99.dev2.dist-info/namespace_packages.txt
odoo10_addon_account_invoice_overdue_warn-10.0.1.0.0.99.dev2.dist-info/top_level.txt
odoo10_addon_account_invoice_overdue_warn-10.0.1.0.0.99.dev2.dist-info/RECORD
